laboro_mail/__init__.py
laboro_mail/ciphers/__init__.py
laboro_mail/files/__init__.py
laboro_mail/imap/__init__.py
laboro_mail/imap/schema/__init__.py
laboro_mail/imap/schema/specification.yml
laboro_mail/pop/__init__.py
laboro_mail/pop/schema/__init__.py
laboro_mail/pop/schema/specification.yml
laboro_mail/smtp/__init__.py
laboro_mail/smtp/schema/__init__.py
laboro_mail/smtp/schema/specification.yml
laboro_mail-0.0.6.dist-info/LICENSE
laboro_mail-0.0.6.dist-info/METADATA
laboro_mail-0.0.6.dist-info/WHEEL
laboro_mail-0.0.6.dist-info/top_level.txt
laboro_mail-0.0.6.dist-info/RECORD
